{
  "direction": "outbound",
  "train_name": "こだま809号",
  "train_type": 1,
  "station_time": [
    {
      "station_name": "東京",
      "arrival": "",
      "departure": "211500",
      "track": 1,
      "status": "stop"
    },
    {
      "station_name": "品川",
      "arrival": "212100",
      "departure": "212200",
      "track": 1,
      "status": "stop"
    },
    {
      "station_name": "新横浜",
      "arrival": "213300",
      "departure": "213400",
      "track": 1,
      "status": "stop"
    },
    {
      "station_name": "小田原",
      "arrival": "215000",
      "departure": "215600",
      "track": 1,
      "status": "stop"
    },
    {
      "station_name": "熱海",
      "arrival": "220300",
      "departure": "220400",
      "track": 1,
      "status": "stop"
    },
    {
      "station_name": "三島",
      "arrival": "221100",
      "departure": "221300",
      "track": 1,
      "status": "stop"
    },
    {
      "station_name": "新富士（静岡県）",
      "arrival": "222200",
      "departure": "222300",
      "track": 1,
      "status": "stop"
    },
    {
      "station_name": "静岡",
      "arrival": "223400",
      "departure": "",
      "track": 1,
      "status": "stop"
    },
    {
      "station_name": "掛川",
      "arrival": "",
      "departure": "",
      "track": 1,
      "status": "pass"
    },
    {
      "station_name": "浜松",
      "arrival": "",
      "departure": "",
      "track": 1,
      "status": "pass"
    },
    {
      "station_name": "豊橋",
      "arrival": "",
      "departure": "",
      "track": 1,
      "status": "pass"
    },
    {
      "station_name": "三河安城",
      "arrival": "",
      "departure": "",
      "track": 1,
      "status": "pass"
    },
    {
      "station_name": "名古屋",
      "arrival": "",
      "departure": "",
      "track": 1,
      "status": "pass"
    },
    {
      "station_name": "岐阜羽島",
      "arrival": "",
      "departure": "",
      "track": 1,
      "status": "pass"
    },
    {
      "station_name": "米原",
      "arrival": "",
      "departure": "",
      "track": 1,
      "status": "pass"
    },
    {
      "station_name": "京都",
      "arrival": "",
      "departure": "",
      "track": 1,
      "status": "pass"
    },
    {
      "station_name": "新大阪",
      "arrival": "",
      "departure": "",
      "track": 1,
      "status": "pass"
    }
  ]
}