{
  "direction": "outbound",
  "train_name": "こだま719号",
  "train_type": 1,
  "station_time": [
    {
      "station_name": "東京",
      "arrival": "",
      "departure": "105700",
      "track": 1,
      "status": "stop"
    },
    {
      "station_name": "品川",
      "arrival": "110300",
      "departure": "110400",
      "track": 1,
      "status": "stop"
    },
    {
      "station_name": "新横浜",
      "arrival": "111400",
      "departure": "111500",
      "track": 1,
      "status": "stop"
    },
    {
      "station_name": "小田原",
      "arrival": "113000",
      "departure": "113500",
      "track": 1,
      "status": "stop"
    },
    {
      "station_name": "熱海",
      "arrival": "114200",
      "departure": "114300",
      "track": 1,
      "status": "stop"
    },
    {
      "station_name": "三島",
      "arrival": "115000",
      "departure": "115500",
      "track": 1,
      "status": "stop"
    },
    {
      "station_name": "新富士（静岡県）",
      "arrival": "120300",
      "departure": "120800",
      "track": 1,
      "status": "stop"
    },
    {
      "station_name": "静岡",
      "arrival": "121800",
      "departure": "122100",
      "track": 1,
      "status": "stop"
    },
    {
      "station_name": "掛川",
      "arrival": "123400",
      "departure": "123600",
      "track": 1,
      "status": "stop"
    },
    {
      "station_name": "浜松",
      "arrival": "124600",
      "departure": "125100",
      "track": 1,
      "status": "stop"
    },
    {
      "station_name": "豊橋",
      "arrival": "130200",
      "departure": "130800",
      "track": 1,
      "status": "stop"
    },
    {
      "station_name": "三河安城",
      "arrival": "132100",
      "departure": "132500",
      "track": 1,
      "status": "stop"
    },
    {
      "station_name": "名古屋",
      "arrival": "133700",
      "departure": "134300",
      "track": 1,
      "status": "stop"
    },
    {
      "station_name": "岐阜羽島",
      "arrival": "135300",
      "departure": "135800",
      "track": 1,
      "status": "stop"
    },
    {
      "station_name": "米原",
      "arrival": "141000",
      "departure": "141600",
      "track": 1,
      "status": "stop"
    },
    {
      "station_name": "京都",
      "arrival": "143400",
      "departure": "143600",
      "track": 1,
      "status": "stop"
    },
    {
      "station_name": "新大阪",
      "arrival": "145100",
      "departure": "",
      "track": 1,
      "status": "stop"
    }
  ]
}